simulator/__init__.py
simulator/generate/datasets.py
simulator/generate/utils.py
simulator/main.py
simulator/send_data_ga/client.py
simulator/send_data_ga/data_types.py
simulator/tools.py
simulator/utils/logger.py
bart_simulator-0.2.1.dist-info/entry_points.txt
bart_simulator-0.2.1.dist-info/WHEEL
bart_simulator-0.2.1.dist-info/METADATA
bart_simulator-0.2.1.dist-info/RECORD
