Metadata-Version: 2.1
Name: bart-simulator
Version: 0.2.1
Summary: Send event views to Google Analytics and Generator customers or products
Home-page: https://github.com/cesarbruschetta/bart-recs
License: Apache-2.0
Keywords: recs,cli,analytics,GA,dataset
Author: Cesar Augusto
Author-email: cesarabruschetta@gmail.com
Requires-Python: >=3.7,<4.0
Classifier: Intended Audience :: Developers
Classifier: License :: OSI Approved :: Apache Software License
Classifier: Operating System :: OS Independent
Classifier: Programming Language :: Python :: 3
Classifier: Programming Language :: Python :: 3.7
Classifier: Programming Language :: Python :: 3.8
Classifier: Topic :: Scientific/Engineering :: Human Machine Interfaces
Classifier: Topic :: Software Development :: Libraries :: Python Modules
Classifier: Topic :: Software Development :: Testing :: Traffic Generation
Requires-Dist: faker (>=4.1.0,<5.0.0)
Requires-Dist: pandas (>=1.0.3,<2.0.0)
Requires-Dist: requests (>=2.23.0,<3.0.0)
Project-URL: Repository, https://github.com/cesarbruschetta/bart-recs
